[{
  "_id": {
    "$oid": "60c683d9a4491003b868e1fd"
  },
  "adreca_id": "1",
  "adreca": "Marina 254",
  "codi_postal": "08041",
  "localitat_id": "1"
},{
  "_id": {
    "$oid": "60c683d9a4491003b868e1fe"
  },
  "adreca_id": "2",
  "adreca": "Fastenrath 66",
  "codi_postal": "08041",
  "localitat_id": "2"
},{
  "_id": {
    "$oid": "60c683d9a4491003b868e1ff"
  },
  "adreca_id": "3",
  "adreca": "Góngora",
  "codi_postal": "08041",
  "localitat_id": "3"
},{
  "_id": {
    "$oid": "60c683d9a4491003b868e200"
  },
  "adreca_id": "4",
  "adreca": "Otro 2224",
  "codi_postal": "08041",
  "localitat_id": "2"
},{
  "_id": {
    "$oid": "60c683d9a4491003b868e201"
  },
  "adreca_id": "5",
  "adreca": "Inexistente 5554",
  "codi_postal": "08041",
  "localitat_id": "1"
}]